PreVectorChunks/__init__.py
PreVectorChunks/admin.py
PreVectorChunks/apps.py
PreVectorChunks/asgi.py
PreVectorChunks/models.py
PreVectorChunks/settings.py
PreVectorChunks/test_loader.py
PreVectorChunks/tests.py
PreVectorChunks/urls.py
PreVectorChunks/wsgi.py
PreVectorChunks/api/__init__.py
PreVectorChunks/api/views.py
PreVectorChunks/migrations/__init__.py
PreVectorChunks/services/__init__.py
PreVectorChunks/services/chunk_documents_crud_vdb.py
PreVectorChunks/utils/__init__.py
PreVectorChunks/utils/file_loader.py
PreVectorChunks/utils/llm_wrapper.py
prevectorchunks-0.1.3.dist-info/METADATA
prevectorchunks-0.1.3.dist-info/WHEEL
prevectorchunks-0.1.3.dist-info/top_level.txt
prevectorchunks-0.1.3.dist-info/RECORD
