Metadata-Version: 2.4
Name: prevectorchunks
Version: 0.1.3
Summary: A Python module that allows to convert a document into chunks to be inserted into pinecone vector database
Author-email: Zul Al-Kabir <zul.developer.2023@gmail.com>
Project-URL: Homepage, https://github.com/yourusername/mydep
Requires-Dist: Django==5.1
Requires-Dist: packaging~=24.1
Requires-Dist: requests~=2.32.3
Requires-Dist: openai~=1.37.1
Requires-Dist: httpx~=0.27.0
Requires-Dist: python-dotenv~=1.0.1
Requires-Dist: django-cors-headers~=4.4.0
Requires-Dist: PyJWT~=2.7.0
Requires-Dist: fastapi~=0.112.2
Requires-Dist: datasets~=4.1.0
Requires-Dist: pinecone~=7.3.0
Requires-Dist: pytesseract~=0.3.13
Requires-Dist: python-docx~=1.2.0
Requires-Dist: PyPDF2~=3.0.1
Requires-Dist: pillow~=11.3.0
